Metadata-Version: 1.1
Name: Flask-Redislite
Version: 0.1.1
Summary: Using Flask with Redislite
Home-page: https://github.com/ViiSiX/FlaskRedislite
Author: Trong-Nghia Nguyen
Author-email: nghia@viisix.space
License: MIT
Download-URL: https://github.com/ViiSiX/FlaskRedislite
Platform: any
Classifier: Development Status :: 5 - Production/Stable
Classifier: Environment :: Web Environment
Classifier: Framework :: Flask
Classifier: Intended Audience :: Developers
Classifier: License :: OSI Approved :: MIT License
Classifier: Operating System :: OS Independent
Classifier: Programming Language :: Python :: 2.7
Classifier: Programming Language :: Python :: 3.5
Classifier: Programming Language :: Python :: 3.6
Classifier: Topic :: Database
Classifier: Topic :: Software Development :: Libraries :: Python Modules
